{
  "category": "N_NONFERROUS",
  "subcategory": "tool_steel",
  "material_count": 1,
  "generated": "2026-01-26T10:23:20.812691",
  "materials": [
    {
      "iso_group": "N",
      "material_type": "aluminum",
      "iso_p_equivalent": "N",
      "physical": {
        "density": 2655.9,
        "melting_point": 896.6,
        "boiling_point": 1699.5,
        "liquidus_temperature": 914.5,
        "solidus_temperature": 851.7,
        "latent_heat_fusion": 343.2,
        "specific_heat": 581.5,
        "thermal_conductivity": 341.2,
        "thermal_expansion": 25.7,
        "electrical_resistivity": 8.46,
        "magnetic_permeability": 1.0,
        "poisson_ratio": 0.311,
        "elastic_modulus": 85.0,
        "shear_modulus": 77.0,
        "bulk_modulus": 216.0
      },
      "mechanical": {
        "hardness": {
          "brinell": 135,
          "vickers": 452.8,
          "rockwell_c": 33.1,
          "rockwell_b": null
        },
        "tensile_strength": {
          "typical": 588.6,
          "min": 529.7,
          "max": 647.4
        },
        "yield_strength": {
          "typical": 319.6,
          "min": 287.6,
          "max": 351.5
        },
        "elongation": 18.8,
        "reduction_of_area": 24.5,
        "impact_strength": 199.5,
        "fatigue_strength": 235.4,
        "fracture_toughness": 98.7,
        "compressive_strength": 647.4,
        "true_fracture_stress": 941.7,
        "true_fracture_strain": 0.2449,
        "strain_rate_sensitivity": 0.0395,
        "shear_strength": 340.0
      },
      "kienzle": {
        "kc1_1": 618.9,
        "mc": 0.2566,
        "kc1_1_milling": 803.2,
        "mc_milling": 0.1789,
        "kc1_1_drilling": 764.2,
        "mc_drilling": 0.2385,
        "kc1_1_boring": 1233,
        "mc_boring": 0.236,
        "kc1_1_reaming": 998,
        "mc_reaming": 0.204
      },
      "johnson_cook": {
        "A": 319.6,
        "B": 672.5,
        "n": 0.4956,
        "C": 0.0249,
        "m": 0.7421,
        "T_melt": 896.6,
        "T_ref": 301.3,
        "epsilon_dot_ref": 0.0022,
        "T_transition": 197
      },
      "taylor": {
        "C": 1403.9,
        "n": 0.2214,
        "C_carbide": 1470.8,
        "n_carbide": 0.3857,
        "C_ceramic": 2045.1,
        "n_ceramic": 0.3861,
        "C_cbn": null,
        "n_cbn": null,
        "C_hss": 165,
        "n_hss": 0.18,
        "C_pcd": 1653,
        "n_pcd": 0.39
      },
      "chip_formation": {
        "chip_type": "continuous",
        "chip_breaking": "moderate",
        "shear_angle": 31.3033576415,
        "chip_compression_ratio": 2.1625734803,
        "built_up_edge_tendency": "high",
        "segmentation_frequency": null,
        "min_chip_thickness": 0.003646292,
        "edge_radius_sensitivity": 0.9394751308
      },
      "tribology": {
        "friction_coefficient": 0.4819425533,
        "friction_coefficient_dry": 0.4364124177,
        "friction_coefficient_flood": 0.1807723921,
        "friction_coefficient_mql": 0.3070981784,
        "wear_coefficient": 5.7869800725,
        "adhesion_tendency": "high",
        "abrasiveness": "moderate",
        "galling_tendency": "low",
        "crater_wear_coefficient": 6.7211400338706e-05,
        "flank_wear_coefficient": 6.8211402512821e-05
      },
      "thermal_machining": {
        "thermal_diffusivity": 125.2125234239,
        "heat_partition_coefficient": 0.6142338256,
        "critical_temperature": 358.6248340007,
        "recrystallization_temperature": 313.7967396521,
        "phase_transformation_temperature": null,
        "maximum_cutting_temperature": 582.765313744,
        "emissivity": 0.7418700832,
        "heat_transfer_coefficient": 10130.6472068585
      },
      "surface_integrity": {
        "residual_stress_tendency": "compressive",
        "work_hardening_depth": 0.2184655519,
        "white_layer_risk": "low",
        "surface_roughness_achievable": 0.3319581644,
        "burr_formation_tendency": "moderate",
        "microstructure_sensitivity": "moderate",
        "minimum_uncut_chip_thickness": 0.0046427035,
        "ploughing_force_coefficient": 0.3438042651
      },
      "machinability": {
        "aisi_rating": 183.6439077035,
        "relative_to_1212": 2.0870017882,
        "machinability_index": 3.478282506,
        "power_constant": 0.8625994803,
        "unit_power": 0.0144604659
      },
      "cutting_recommendations": {
        "turning": {
          "speed_roughing": 216.0074122187,
          "speed_finishing": 458.9011861125,
          "feed_roughing": 0.414715806,
          "feed_finishing": 0.1385507499,
          "doc_roughing": 1.1466103579,
          "doc_finishing": 0.6263671577
        },
        "milling": {
          "speed_roughing": 291.8804340917,
          "speed_finishing": 207.9366011479,
          "feed_per_tooth_roughing": 0.074660756,
          "feed_per_tooth_finishing": 0.0486373359,
          "doc_roughing": 2.873722585,
          "doc_finishing": 0.3388029501,
          "woc_roughing": 0.9052264165,
          "woc_finishing": 0.2985241198
        },
        "drilling": {
          "speed": 195.6655458768,
          "feed_per_rev": 0.303727585,
          "peck_depth_ratio": 0.4282829196
        },
        "tool_material": {
          "recommended_grade": "Coated carbide",
          "coating_recommendation": "DLC",
          "geometry_recommendation": "Positive rake"
        },
        "coolant": {
          "type": "Flood emulsion",
          "pressure": 43.6032778146,
          "flow_rate": 41.7156109269
        }
      },
      "process_specific": {
        "grinding_ratio": 13.6252579008,
        "edm_machinability": 56.5983968097,
        "laser_absorptivity": 0.5321218634,
        "weldability_rating": "excellent"
      },
      "name": "A201-T7 High Strength Cast",
      "material_id": "NF-A201-T7-HIGH-STRENGTH-CAST-ENH",
      "subcategory": "general",
      "condition": "as_supplied",
      "data_quality": "estimated",
      "data_sources": [
        "PRISM_enhanced_v10"
      ],
      "surface": {
        "achievable_ra_turning": 0.4,
        "achievable_ra_milling": 0.8,
        "achievable_ra_grinding": 0.1,
        "surface_integrity_sensitivity": "low",
        "white_layer_risk": "none"
      },
      "thermal": {
        "cutting_temperature_factor": 0.15,
        "heat_partition_ratio": 0.5,
        "thermal_softening_onset": 200,
        "hot_hardness_retention": "low",
        "cryogenic_machinability": "marginal"
      },
      "weldability": {
        "rating": "good",
        "preheat_temperature": 0,
        "postweld_treatment": "none_required"
      },
      "composition": {
        "note": "composition_data_pending"
      },
      "standards": {
        "note": "cross_reference_pending"
      },
      "statistics": {
        "dataPoints": 40,
        "confidenceLevel": 0.65,
        "standardDeviation": {
          "speed": 3.2,
          "force": 165,
          "toolLife": 11
        },
        "sources": [
          "PRISM_enhanced_v10"
        ],
        "lastValidated": "2026-Q1",
        "reliability": "ESTIMATED"
      },
      "_verified": {
        "session": 99,
        "date": "2026-02-27",
        "method": "batch_enhancement_v10_physics_correlation",
        "params": 164,
        "prior_method": null,
        "prior_params": null
      }
    }
  ],
  "enhanced_date": "2026-01-26T10:45:58.937268",
  "physics_complete": true,
  "physics_mode": "accurate",
  "_enhanced": {
    "timestamp": "2026-01-27T13:51:21.660134",
    "version": "1.0"
  },
  "_enhancement_iteration": "2026-01-27T14:09:11.523653",
  "_complete_enhanced": {
    "timestamp": "2026-01-27T14:13:25.599061",
    "version": "2.0"
  }
}